pyegsnrc/__init__.py
pyegsnrc/__main__.py
pyegsnrc/data/__init__.py
pyegsnrc/data/bremsstrahlung/README.md
pyegsnrc/data/bremsstrahlung/Z001.csv
pyegsnrc/data/bremsstrahlung/Z002.csv
pyegsnrc/data/bremsstrahlung/Z003.csv
pyegsnrc/data/bremsstrahlung/Z004.csv
pyegsnrc/data/bremsstrahlung/Z005.csv
pyegsnrc/data/bremsstrahlung/Z006.csv
pyegsnrc/data/bremsstrahlung/Z007.csv
pyegsnrc/data/bremsstrahlung/Z008.csv
pyegsnrc/data/bremsstrahlung/Z009.csv
pyegsnrc/data/bremsstrahlung/Z010.csv
pyegsnrc/data/bremsstrahlung/Z011.csv
pyegsnrc/data/bremsstrahlung/Z012.csv
pyegsnrc/data/bremsstrahlung/Z013.csv
pyegsnrc/data/bremsstrahlung/Z014.csv
pyegsnrc/data/bremsstrahlung/Z015.csv
pyegsnrc/data/bremsstrahlung/Z016.csv
pyegsnrc/data/bremsstrahlung/Z017.csv
pyegsnrc/data/bremsstrahlung/Z018.csv
pyegsnrc/data/bremsstrahlung/Z019.csv
pyegsnrc/data/bremsstrahlung/Z020.csv
pyegsnrc/data/bremsstrahlung/Z021.csv
pyegsnrc/data/bremsstrahlung/Z022.csv
pyegsnrc/data/bremsstrahlung/Z023.csv
pyegsnrc/data/bremsstrahlung/Z024.csv
pyegsnrc/data/bremsstrahlung/Z025.csv
pyegsnrc/data/bremsstrahlung/Z026.csv
pyegsnrc/data/bremsstrahlung/Z027.csv
pyegsnrc/data/bremsstrahlung/Z028.csv
pyegsnrc/data/bremsstrahlung/Z029.csv
pyegsnrc/data/bremsstrahlung/Z030.csv
pyegsnrc/data/bremsstrahlung/Z031.csv
pyegsnrc/data/bremsstrahlung/Z032.csv
pyegsnrc/data/bremsstrahlung/Z033.csv
pyegsnrc/data/bremsstrahlung/Z034.csv
pyegsnrc/data/bremsstrahlung/Z035.csv
pyegsnrc/data/bremsstrahlung/Z036.csv
pyegsnrc/data/bremsstrahlung/Z037.csv
pyegsnrc/data/bremsstrahlung/Z038.csv
pyegsnrc/data/bremsstrahlung/Z039.csv
pyegsnrc/data/bremsstrahlung/Z040.csv
pyegsnrc/data/bremsstrahlung/Z041.csv
pyegsnrc/data/bremsstrahlung/Z042.csv
pyegsnrc/data/bremsstrahlung/Z043.csv
pyegsnrc/data/bremsstrahlung/Z044.csv
pyegsnrc/data/bremsstrahlung/Z045.csv
pyegsnrc/data/bremsstrahlung/Z046.csv
pyegsnrc/data/bremsstrahlung/Z047.csv
pyegsnrc/data/bremsstrahlung/Z048.csv
pyegsnrc/data/bremsstrahlung/Z049.csv
pyegsnrc-0.2.0.dist-info/entry_points.txt
pyegsnrc-0.2.0.dist-info/WHEEL
pyegsnrc-0.2.0.dist-info/METADATA
pyegsnrc-0.2.0.dist-info/RECORD
